{
  "sim_day": "2026-11-11",
  "n_services": 1200,
  "scenario": "normal",
  "seed": 7,
  "timestamp": "2025-12-01T16:22:39.783166+00:00",
  "per_city": {
    "1": {
      "n_total": 220,
      "historic_static_mean": 0.7788778877887789,
      "historic_dynamic_mean": 0.22112211221122113,
      "multiplier": 1.0125095466604668,
      "static_prop_sim": 0.7886212970688784,
      "dynamic_prop_sim": 0.2113787029311216,
      "n_static": 173,
      "n_dynamic": 47
    },
    "1004": {
      "n_total": 233,
      "historic_static_mean": 0.8136645962732919,
      "historic_dynamic_mean": 0.18633540372670807,
      "multiplier": 1.0397213800969576,
      "static_prop_sim": 0.8459844769733009,
      "dynamic_prop_sim": 0.15401552302669907,
      "n_static": 197,
      "n_dynamic": 36
    },
    "126": {
      "n_total": 25,
      "historic_static_mean": 0.7428571428571429,
      "historic_dynamic_mean": 0.2571428571428571,
      "multiplier": 1.0275685690245193,
      "static_prop_sim": 0.7633366512753572,
      "dynamic_prop_sim": 0.23666334872464279,
      "n_static": 19,
      "n_dynamic": 6
    },
    "149": {
      "n_total": 695,
      "historic_static_mean": 0.6715328467153284,
      "historic_dynamic_mean": 0.3284671532846715,
      "multiplier": 0.9725207189990591,
      "static_prop_sim": 0.6530796069190762,
      "dynamic_prop_sim": 0.3469203930809238,
      "n_static": 454,
      "n_dynamic": 241
    },
    "150": {
      "n_total": 5,
      "historic_static_mean": 0.42857142857142855,
      "historic_dynamic_mean": 0.5714285714285714,
      "multiplier": 0.9800166284911225,
      "static_prop_sim": 0.4200071264961953,
      "dynamic_prop_sim": 0.5799928735038047,
      "n_static": 2,
      "n_dynamic": 3
    },
    "830": {
      "n_total": 1,
      "historic_static_mean": 1.0,
      "historic_dynamic_mean": 0.0,
      "multiplier": 1.0373553445396262,
      "static_prop_sim": 1.0,
      "dynamic_prop_sim": 0.0,
      "n_static": 1,
      "n_dynamic": 0
    },
    "844": {
      "n_total": 21,
      "historic_static_mean": 0.5862068965517241,
      "historic_dynamic_mean": 0.41379310344827586,
      "multiplier": 0.9505265304565574,
      "static_prop_sim": 0.5572052075090164,
      "dynamic_prop_sim": 0.44279479249098364,
      "n_static": 12,
      "n_dynamic": 9
    }
  }
}